{"3b0cc11e31edc878457d701ed55b9a48":{"statistic":{"failed":0,"broken":0,"skipped":0,"passed":1,"unknown":0,"total":1},"items":[{"uid":"8a9e72c268c228fd","reportUrl":"https://DSahalatyi.github.io/test/24//#testresult/8a9e72c268c228fd","status":"passed","time":{"start":1677436026653,"stop":1677436026698,"duration":45}}]},"e7888c08c99ba497916dc39b01fc65de":{"statistic":{"failed":0,"broken":0,"skipped":0,"passed":1,"unknown":0,"total":1},"items":[{"uid":"3535fcaa4d492f0b","reportUrl":"https://DSahalatyi.github.io/test/24//#testresult/3535fcaa4d492f0b","status":"passed","time":{"start":1677436017797,"stop":1677436017803,"duration":6}}]},"9f55d7cc89d451bba8af8319834eb7f1":{"statistic":{"failed":0,"broken":0,"skipped":0,"passed":1,"unknown":0,"total":1},"items":[{"uid":"6694fc68a935e17e","reportUrl":"https://DSahalatyi.github.io/test/24//#testresult/6694fc68a935e17e","status":"passed","time":{"start":1677436015411,"stop":1677436015458,"duration":47}}]},"60a403ae5f0d15162ebf635047776e01":{"statistic":{"failed":0,"broken":0,"skipped":0,"passed":1,"unknown":0,"total":1},"items":[{"uid":"95a203aa2d79cd3a","reportUrl":"https://DSahalatyi.github.io/test/24//#testresult/95a203aa2d79cd3a","status":"passed","time":{"start":1677436026145,"stop":1677436026191,"duration":46}}]},"c17c212afe66e1fbdbde6d847201f5cd":{"statistic":{"failed":0,"broken":0,"skipped":0,"passed":1,"unknown":0,"total":1},"items":[{"uid":"32552977da08aa0","reportUrl":"https://DSahalatyi.github.io/test/24//#testresult/32552977da08aa0","status":"passed","time":{"start":1677436022992,"stop":1677436023000,"duration":8}}]},"e238d20811c0c7dcd03f11f5feca95dd":{"statistic":{"failed":0,"broken":0,"skipped":0,"passed":1,"unknown":0,"total":1},"items":[{"uid":"d08ea3619c8cc62d","reportUrl":"https://DSahalatyi.github.io/test/24//#testresult/d08ea3619c8cc62d","status":"passed","time":{"start":1677436011182,"stop":1677436011230,"duration":48}}]},"8ee74ae66550fb9282be7885ce8e56ef":{"statistic":{"failed":0,"broken":0,"skipped":0,"passed":1,"unknown":0,"total":1},"items":[{"uid":"9e8c093478172cca","reportUrl":"https://DSahalatyi.github.io/test/24//#testresult/9e8c093478172cca","status":"passed","time":{"start":1677436028044,"stop":1677436028051,"duration":7}}]},"c77ba0555cf405771bbad78da7ab1373":{"statistic":{"failed":0,"broken":0,"skipped":0,"passed":1,"unknown":0,"total":1},"items":[{"uid":"b38a43bdc640a9fb","reportUrl":"https://DSahalatyi.github.io/test/24//#testresult/b38a43bdc640a9fb","status":"passed","time":{"start":1677436026402,"stop":1677436026451,"duration":49}}]},"fd67452d1fa072546006db49cde893d1":{"statistic":{"failed":0,"broken":0,"skipped":0,"passed":1,"unknown":0,"total":1},"items":[{"uid":"6ad513ad271c6b02","reportUrl":"https://DSahalatyi.github.io/test/24//#testresult/6ad513ad271c6b02","status":"passed","time":{"start":1677436024779,"stop":1677436024786,"duration":7}}]},"a63ed2b0eec7a15a82f18a58c9f8b12f":{"statistic":{"failed":0,"broken":0,"skipped":0,"passed":1,"unknown":0,"total":1},"items":[{"uid":"2d4fbcec53b5b530","reportUrl":"https://DSahalatyi.github.io/test/24//#testresult/2d4fbcec53b5b530","status":"passed","time":{"start":1677436009826,"stop":1677436009832,"duration":6}}]},"c7dedcf7dcca12115eab4ee3ddc54425":{"statistic":{"failed":0,"broken":0,"skipped":0,"passed":1,"unknown":0,"total":1},"items":[{"uid":"318064213fbbaebc","reportUrl":"https://DSahalatyi.github.io/test/24//#testresult/318064213fbbaebc","status":"passed","time":{"start":1677436025460,"stop":1677436025470,"duration":10}}]},"e8cbc8c11f6e797697c3c0dae2b072c1":{"statistic":{"failed":0,"broken":0,"skipped":0,"passed":1,"unknown":0,"total":1},"items":[{"uid":"e9f94fb68a90960","reportUrl":"https://DSahalatyi.github.io/test/24//#testresult/e9f94fb68a90960","status":"passed","time":{"start":1677436022655,"stop":1677436022665,"duration":10}}]},"8e833c0f1e6a0e19852530d4658d7a9b":{"statistic":{"failed":0,"broken":0,"skipped":0,"passed":1,"unknown":0,"total":1},"items":[{"uid":"fafd98057a5e28c7","reportUrl":"https://DSahalatyi.github.io/test/24//#testresult/fafd98057a5e28c7","status":"passed","time":{"start":1677436011399,"stop":1677436011446,"duration":47}}]},"7e6af4ddaa631482f799688359f853f5":{"statistic":{"failed":0,"broken":0,"skipped":0,"passed":1,"unknown":0,"total":1},"items":[{"uid":"e1996fe26fc919cf","reportUrl":"https://DSahalatyi.github.io/test/24//#testresult/e1996fe26fc919cf","status":"passed","time":{"start":1677436027825,"stop":1677436027831,"duration":6}}]},"0d20fc5e95607705f46d39b4ff212819":{"statistic":{"failed":0,"broken":0,"skipped":0,"passed":1,"unknown":0,"total":1},"items":[{"uid":"298155e24788934f","reportUrl":"https://DSahalatyi.github.io/test/24//#testresult/298155e24788934f","status":"passed","time":{"start":1677436017372,"stop":1677436017421,"duration":49}}]},"21036b78c88ed33544e8aa0c42747450":{"statistic":{"failed":0,"broken":0,"skipped":0,"passed":1,"unknown":0,"total":1},"items":[{"uid":"e53261a9fc74f0af","reportUrl":"https://DSahalatyi.github.io/test/24//#testresult/e53261a9fc74f0af","status":"passed","time":{"start":1677436020299,"stop":1677436020304,"duration":5}}]},"1c699cbe42bdc9a00be7753df5a2a6e2":{"statistic":{"failed":0,"broken":0,"skipped":0,"passed":1,"unknown":0,"total":1},"items":[{"uid":"f7baeb4892ee45eb","reportUrl":"https://DSahalatyi.github.io/test/24//#testresult/f7baeb4892ee45eb","status":"passed","time":{"start":1677436010723,"stop":1677436010791,"duration":68}}]},"6ca28243590d99ac1d42010a3425cdb9":{"statistic":{"failed":0,"broken":0,"skipped":0,"passed":1,"unknown":0,"total":1},"items":[{"uid":"69140ad59ec4addd","reportUrl":"https://DSahalatyi.github.io/test/24//#testresult/69140ad59ec4addd","status":"passed","time":{"start":1677436007696,"stop":1677436007701,"duration":5}}]},"305625ad87c62837eff5fdee7700f9ab":{"statistic":{"failed":0,"broken":0,"skipped":0,"passed":1,"unknown":0,"total":1},"items":[{"uid":"514e51f71c841e1a","reportUrl":"https://DSahalatyi.github.io/test/24//#testresult/514e51f71c841e1a","status":"passed","time":{"start":1677436019320,"stop":1677436019323,"duration":3}}]},"840eb041ecdee065bd60b1d9b0184407":{"statistic":{"failed":0,"broken":0,"skipped":0,"passed":1,"unknown":0,"total":1},"items":[{"uid":"892eecb8a5c76979","reportUrl":"https://DSahalatyi.github.io/test/24//#testresult/892eecb8a5c76979","status":"passed","time":{"start":1677436021435,"stop":1677436021485,"duration":50}}]},"23b1a7dcc4c89f2b4d120546d9e3405f":{"statistic":{"failed":0,"broken":0,"skipped":0,"passed":1,"unknown":0,"total":1},"items":[{"uid":"f24e9bc38a887f9d","reportUrl":"https://DSahalatyi.github.io/test/24//#testresult/f24e9bc38a887f9d","status":"passed","time":{"start":1677436008122,"stop":1677436008132,"duration":10}}]},"43501adef220abd713f7ec2e0da6dba7":{"statistic":{"failed":0,"broken":0,"skipped":0,"passed":1,"unknown":0,"total":1},"items":[{"uid":"f4e6d9c31c1ef2f8","reportUrl":"https://DSahalatyi.github.io/test/24//#testresult/f4e6d9c31c1ef2f8","status":"passed","time":{"start":1677436028474,"stop":1677436028479,"duration":5}}]},"bc8eaef8c885e5a4c4addd2221d5e864":{"statistic":{"failed":0,"broken":0,"skipped":0,"passed":1,"unknown":0,"total":1},"items":[{"uid":"35f3ff4e3b9a7481","reportUrl":"https://DSahalatyi.github.io/test/24//#testresult/35f3ff4e3b9a7481","status":"passed","time":{"start":1677436023911,"stop":1677436023915,"duration":4}}]},"dd748dfcfa5d051b9d8fc821ee9a0300":{"statistic":{"failed":0,"broken":0,"skipped":0,"passed":1,"unknown":0,"total":1},"items":[{"uid":"2901468b938c9281","reportUrl":"https://DSahalatyi.github.io/test/24//#testresult/2901468b938c9281","status":"passed","time":{"start":1677436010402,"stop":1677436010453,"duration":51}}]},"f75030c73db6b5aae034dc8b6fb28b07":{"statistic":{"failed":0,"broken":0,"skipped":0,"passed":1,"unknown":0,"total":1},"items":[{"uid":"7d7ecd01e85f2611","reportUrl":"https://DSahalatyi.github.io/test/24//#testresult/7d7ecd01e85f2611","status":"passed","time":{"start":1677436008247,"stop":1677436008309,"duration":62}}]},"6dd853c453eb4c82fddae363046adc5e":{"statistic":{"failed":0,"broken":0,"skipped":0,"passed":1,"unknown":0,"total":1},"items":[{"uid":"3ffa53f0462c71a7","reportUrl":"https://DSahalatyi.github.io/test/24//#testresult/3ffa53f0462c71a7","status":"passed","time":{"start":1677436028685,"stop":1677436028691,"duration":6}}]},"475356b8822f39d5e8ffc38d64cd94ca":{"statistic":{"failed":0,"broken":0,"skipped":0,"passed":1,"unknown":0,"total":1},"items":[{"uid":"409cf02cfbea95e6","reportUrl":"https://DSahalatyi.github.io/test/24//#testresult/409cf02cfbea95e6","status":"passed","time":{"start":1677436015143,"stop":1677436015193,"duration":50}}]},"84c4cda179fce0ba3c01faca0bf8aed2":{"statistic":{"failed":0,"broken":0,"skipped":0,"passed":1,"unknown":0,"total":1},"items":[{"uid":"8666ea348628dcdb","reportUrl":"https://DSahalatyi.github.io/test/24//#testresult/8666ea348628dcdb","status":"passed","time":{"start":1677436008605,"stop":1677436008651,"duration":46}}]},"73e3d632c2cfda646bfe9599faaa7bb0":{"statistic":{"failed":0,"broken":0,"skipped":0,"passed":1,"unknown":0,"total":1},"items":[{"uid":"4658756e8afd66d1","reportUrl":"https://DSahalatyi.github.io/test/24//#testresult/4658756e8afd66d1","status":"passed","time":{"start":1677436016219,"stop":1677436016266,"duration":47}}]},"7edcc4b76ad3f6fecd5fc3c3ee1a4e18":{"statistic":{"failed":0,"broken":0,"skipped":0,"passed":1,"unknown":0,"total":1},"items":[{"uid":"d896b729c59cb6e5","reportUrl":"https://DSahalatyi.github.io/test/24//#testresult/d896b729c59cb6e5","status":"passed","time":{"start":1677436015951,"stop":1677436015998,"duration":47}}]},"4b769dbac4715ad56182297538a36980":{"statistic":{"failed":0,"broken":0,"skipped":0,"passed":1,"unknown":0,"total":1},"items":[{"uid":"5ebf999ee09b9f62","reportUrl":"https://DSahalatyi.github.io/test/24//#testresult/5ebf999ee09b9f62","status":"passed","time":{"start":1677436027153,"stop":1677436027196,"duration":43}}]},"e13d9ce9443d502b199c726e811eae9d":{"statistic":{"failed":0,"broken":0,"skipped":0,"passed":1,"unknown":0,"total":1},"items":[{"uid":"ffff68e0fd325d9d","reportUrl":"https://DSahalatyi.github.io/test/24//#testresult/ffff68e0fd325d9d","status":"passed","time":{"start":1677436009151,"stop":1677436009156,"duration":5}}]},"fbeddbee3a2dadb62aee77782d54b1e9":{"statistic":{"failed":0,"broken":0,"skipped":0,"passed":1,"unknown":0,"total":1},"items":[{"uid":"209e3f7c28ab8108","reportUrl":"https://DSahalatyi.github.io/test/24//#testresult/209e3f7c28ab8108","status":"passed","time":{"start":1677436018302,"stop":1677436018307,"duration":5}}]},"75d8251c93d642b23c3d776abdafd70e":{"statistic":{"failed":0,"broken":0,"skipped":0,"passed":1,"unknown":0,"total":1},"items":[{"uid":"7b118313c5d6ff4b","reportUrl":"https://DSahalatyi.github.io/test/24//#testresult/7b118313c5d6ff4b","status":"passed","time":{"start":1677436025229,"stop":1677436025232,"duration":3}}]},"266c5d6c3981a9cafa33ce63439986f4":{"statistic":{"failed":0,"broken":0,"skipped":0,"passed":1,"unknown":0,"total":1},"items":[{"uid":"b9fdee58f142859e","reportUrl":"https://DSahalatyi.github.io/test/24//#testresult/b9fdee58f142859e","status":"passed","time":{"start":1677436018133,"stop":1677436018142,"duration":9}}]},"ac2385dd1113809941c2704664f85dd9":{"statistic":{"failed":0,"broken":0,"skipped":0,"passed":1,"unknown":0,"total":1},"items":[{"uid":"3d5cca8b4e1ad7a4","reportUrl":"https://DSahalatyi.github.io/test/24//#testresult/3d5cca8b4e1ad7a4","status":"passed","time":{"start":1677436007918,"stop":1677436007967,"duration":49}}]},"5dcf655aab2b40734c5b9c5adf937383":{"statistic":{"failed":0,"broken":0,"skipped":0,"passed":1,"unknown":0,"total":1},"items":[{"uid":"62440efbf31b6682","reportUrl":"https://DSahalatyi.github.io/test/24//#testresult/62440efbf31b6682","status":"passed","time":{"start":1677436021656,"stop":1677436021705,"duration":49}}]},"3a79ab251a3be896e3d89f8be335903d":{"statistic":{"failed":0,"broken":0,"skipped":0,"passed":1,"unknown":0,"total":1},"items":[{"uid":"886a5b549115eea3","reportUrl":"https://DSahalatyi.github.io/test/24//#testresult/886a5b549115eea3","status":"passed","time":{"start":1677436022486,"stop":1677436022494,"duration":8}}]},"c264b29cf40c8feb80ada6ca7fc03b0f":{"statistic":{"failed":0,"broken":0,"skipped":0,"passed":1,"unknown":0,"total":1},"items":[{"uid":"13012d8c5c33726d","reportUrl":"https://DSahalatyi.github.io/test/24//#testresult/13012d8c5c33726d","status":"passed","time":{"start":1677436008227,"stop":1677436008236,"duration":9}}]},"08e2d68e8236aedd59d6bc5fdc6957e8":{"statistic":{"failed":0,"broken":0,"skipped":0,"passed":1,"unknown":0,"total":1},"items":[{"uid":"2aae90e910148921","reportUrl":"https://DSahalatyi.github.io/test/24//#testresult/2aae90e910148921","status":"passed","time":{"start":1677436016483,"stop":1677436016532,"duration":49}}]},"0fe6fb49a2216fb063b5ba9da07e88ec":{"statistic":{"failed":0,"broken":0,"skipped":0,"passed":1,"unknown":0,"total":1},"items":[{"uid":"7bc3137286cfe830","reportUrl":"https://DSahalatyi.github.io/test/24//#testresult/7bc3137286cfe830","status":"passed","time":{"start":1677436027611,"stop":1677436027618,"duration":7}}]},"b0c29b3d4506246bb109901d07165e36":{"statistic":{"failed":0,"broken":0,"skipped":0,"passed":1,"unknown":0,"total":1},"items":[{"uid":"498e3810d87444f0","reportUrl":"https://DSahalatyi.github.io/test/24//#testresult/498e3810d87444f0","status":"passed","time":{"start":1677436023206,"stop":1677436023211,"duration":5}}]},"8995aeabd58e0f063588e426de098ecb":{"statistic":{"failed":0,"broken":0,"skipped":0,"passed":1,"unknown":0,"total":1},"items":[{"uid":"78da0509cc47a80a","reportUrl":"https://DSahalatyi.github.io/test/24//#testresult/78da0509cc47a80a","status":"passed","time":{"start":1677436008450,"stop":1677436008494,"duration":44}}]},"137ce8f9825f062be9627d8e463980a7":{"statistic":{"failed":0,"broken":0,"skipped":0,"passed":1,"unknown":0,"total":1},"items":[{"uid":"8a87cb003a4e40be","reportUrl":"https://DSahalatyi.github.io/test/24//#testresult/8a87cb003a4e40be","status":"passed","time":{"start":1677436013128,"stop":1677436013131,"duration":3}}]},"88795c01e670e66e2540429460f7bca7":{"statistic":{"failed":0,"broken":0,"skipped":0,"passed":1,"unknown":0,"total":1},"items":[{"uid":"9470a6a1fd40ba73","reportUrl":"https://DSahalatyi.github.io/test/24//#testresult/9470a6a1fd40ba73","status":"passed","time":{"start":1677436007801,"stop":1677436007842,"duration":41}}]},"d75e6536a4db1a1059616c8b5d5c13fc":{"statistic":{"failed":0,"broken":0,"skipped":0,"passed":1,"unknown":0,"total":1},"items":[{"uid":"1ef85e0960ce9619","reportUrl":"https://DSahalatyi.github.io/test/24//#testresult/1ef85e0960ce9619","status":"passed","time":{"start":1677436025061,"stop":1677436025067,"duration":6}}]},"42a0c9dbae6284c6416d9756a69b3cf5":{"statistic":{"failed":0,"broken":0,"skipped":0,"passed":1,"unknown":0,"total":1},"items":[{"uid":"313d58d03f575397","reportUrl":"https://DSahalatyi.github.io/test/24//#testresult/313d58d03f575397","status":"passed","time":{"start":1677436014499,"stop":1677436014508,"duration":9}}]},"8c8edb3a4bb81bbbad599e14e8e6a204":{"statistic":{"failed":0,"broken":0,"skipped":0,"passed":1,"unknown":0,"total":1},"items":[{"uid":"846e897a3a38a0bf","reportUrl":"https://DSahalatyi.github.io/test/24//#testresult/846e897a3a38a0bf","status":"passed","time":{"start":1677436024201,"stop":1677436024210,"duration":9}}]},"80835a7d174fc5232b910fe0d83cac52":{"statistic":{"failed":0,"broken":0,"skipped":0,"passed":1,"unknown":0,"total":1},"items":[{"uid":"24639b361498e6db","reportUrl":"https://DSahalatyi.github.io/test/24//#testresult/24639b361498e6db","status":"passed","time":{"start":1677436026902,"stop":1677436026945,"duration":43}}]},"439639cff638aacd07c19ad1a6b0085f":{"statistic":{"failed":0,"broken":0,"skipped":0,"passed":1,"unknown":0,"total":1},"items":[{"uid":"cbecd7404dcf6410","reportUrl":"https://DSahalatyi.github.io/test/24//#testresult/cbecd7404dcf6410","status":"passed","time":{"start":1677436017967,"stop":1677436017972,"duration":5}}]},"521c51e1dc0e0f290f3265a0e4428308":{"statistic":{"failed":0,"broken":0,"skipped":0,"passed":1,"unknown":0,"total":1},"items":[{"uid":"7b459392f1c843a8","reportUrl":"https://DSahalatyi.github.io/test/24//#testresult/7b459392f1c843a8","status":"passed","time":{"start":1677436008021,"stop":1677436008028,"duration":7}}]},"40a23e0118b1c540ca0edd9304555dc3":{"statistic":{"failed":0,"broken":0,"skipped":0,"passed":1,"unknown":0,"total":1},"items":[{"uid":"c2c5d94f9ee96607","reportUrl":"https://DSahalatyi.github.io/test/24//#testresult/c2c5d94f9ee96607","status":"passed","time":{"start":1677436019733,"stop":1677436019743,"duration":10}}]},"e5acdb4e667c18dc9d67bdbb39c075e7":{"statistic":{"failed":0,"broken":0,"skipped":0,"passed":1,"unknown":0,"total":1},"items":[{"uid":"2f58fba6d45244bd","reportUrl":"https://DSahalatyi.github.io/test/24//#testresult/2f58fba6d45244bd","status":"passed","time":{"start":1677436008500,"stop":1677436008546,"duration":46}}]},"8b1ee7712d3a006e081e3c43954d0c2b":{"statistic":{"failed":0,"broken":0,"skipped":0,"passed":1,"unknown":0,"total":1},"items":[{"uid":"7ed60bfa7563f97c","reportUrl":"https://DSahalatyi.github.io/test/24//#testresult/7ed60bfa7563f97c","status":"passed","time":{"start":1677436013796,"stop":1677436013798,"duration":2}}]},"b93305e804b6dc4b4bee02f07c2d3603":{"statistic":{"failed":0,"broken":0,"skipped":0,"passed":1,"unknown":0,"total":1},"items":[{"uid":"2d4b5acd42cacc50","reportUrl":"https://DSahalatyi.github.io/test/24//#testresult/2d4b5acd42cacc50","status":"passed","time":{"start":1677436013352,"stop":1677436013358,"duration":6}}]},"2b0606e8b2b5ade1d6a74ea66cffe22b":{"statistic":{"failed":0,"broken":0,"skipped":1,"passed":0,"unknown":0,"total":1},"items":[{"uid":"d98f6949c81e865e","reportUrl":"https://DSahalatyi.github.io/test/24//#testresult/d98f6949c81e865e","status":"skipped","statusDetails":"Skipped: crashes server","time":{"start":1677436016804,"stop":1677436016804,"duration":0}}]},"30d68d3f1b05e0be025c7fa705e14057":{"statistic":{"failed":0,"broken":0,"skipped":0,"passed":1,"unknown":0,"total":1},"items":[{"uid":"f5daba2c0699425e","reportUrl":"https://DSahalatyi.github.io/test/24//#testresult/f5daba2c0699425e","status":"passed","time":{"start":1677436016751,"stop":1677436016797,"duration":46}}]},"06af4d1d277931843e5cea4e9dcb824a":{"statistic":{"failed":0,"broken":0,"skipped":0,"passed":1,"unknown":0,"total":1},"items":[{"uid":"8b574793a0f48b51","reportUrl":"https://DSahalatyi.github.io/test/24//#testresult/8b574793a0f48b51","status":"passed","time":{"start":1677436023372,"stop":1677436023379,"duration":7}}]},"ca2de1981a72454126417ba49b1d719f":{"statistic":{"failed":0,"broken":0,"skipped":0,"passed":1,"unknown":0,"total":1},"items":[{"uid":"2dd547097ba05943","reportUrl":"https://DSahalatyi.github.io/test/24//#testresult/2dd547097ba05943","status":"passed","time":{"start":1677436021937,"stop":1677436021942,"duration":5}}]},"adc0ef3f6708ea7f5dbfec1e4ebd6c93":{"statistic":{"failed":0,"broken":0,"skipped":0,"passed":1,"unknown":0,"total":1},"items":[{"uid":"4a8e2f651c054f35","reportUrl":"https://DSahalatyi.github.io/test/24//#testresult/4a8e2f651c054f35","status":"passed","time":{"start":1677436015688,"stop":1677436015733,"duration":45}}]},"af0c5461548c02ecb006515ae9ac45ce":{"statistic":{"failed":0,"broken":0,"skipped":1,"passed":0,"unknown":0,"total":1},"items":[{"uid":"a909cb4faf497851","reportUrl":"https://DSahalatyi.github.io/test/24//#testresult/a909cb4faf497851","status":"skipped","statusDetails":"XFAIL\n\nAssertionError: assert 500 == 409\n +  where 500 = <Response [500 Internal Server Error]>.status_code","time":{"start":1677436011830,"stop":1677436011886,"duration":56}}]},"266c90f9e0a24d44f76ef7d55f428192":{"statistic":{"failed":0,"broken":0,"skipped":0,"passed":1,"unknown":0,"total":1},"items":[{"uid":"afe57ebaec112189","reportUrl":"https://DSahalatyi.github.io/test/24//#testresult/afe57ebaec112189","status":"passed","time":{"start":1677436021002,"stop":1677436021051,"duration":49}}]},"38a28063ad982820f8bcefefe1f1ef3a":{"statistic":{"failed":0,"broken":0,"skipped":0,"passed":1,"unknown":0,"total":1},"items":[{"uid":"a687f402afa10c30","reportUrl":"https://DSahalatyi.github.io/test/24//#testresult/a687f402afa10c30","status":"passed","time":{"start":1677436008552,"stop":1677436008598,"duration":46}}]},"7d8d8990038ccde6d55a187d8dd3810e":{"statistic":{"failed":0,"broken":0,"skipped":0,"passed":1,"unknown":0,"total":1},"items":[{"uid":"ba6403c947c46898","reportUrl":"https://DSahalatyi.github.io/test/24//#testresult/ba6403c947c46898","status":"passed","time":{"start":1677436019496,"stop":1677436019501,"duration":5}}]},"caeeb4668b4a5bfbf83f1dac2b8c1cc1":{"statistic":{"failed":0,"broken":0,"skipped":0,"passed":1,"unknown":0,"total":1},"items":[{"uid":"d64343ecc9cd7772","reportUrl":"https://DSahalatyi.github.io/test/24//#testresult/d64343ecc9cd7772","status":"passed","time":{"start":1677436023547,"stop":1677436023552,"duration":5}}]},"31c6e32ce2ff32b024cc0913876bf4ae":{"statistic":{"failed":0,"broken":0,"skipped":0,"passed":1,"unknown":0,"total":1},"items":[{"uid":"ce3e34bfe21e370d","reportUrl":"https://DSahalatyi.github.io/test/24//#testresult/ce3e34bfe21e370d","status":"passed","time":{"start":1677436027396,"stop":1677436027406,"duration":10}}]},"41ce8d53204400687d4631f62db87857":{"statistic":{"failed":0,"broken":0,"skipped":0,"passed":1,"unknown":0,"total":1},"items":[{"uid":"effc0141d198af37","reportUrl":"https://DSahalatyi.github.io/test/24//#testresult/effc0141d198af37","status":"passed","time":{"start":1677436007565,"stop":1677436007640,"duration":75}}]},"37103deeff7fae1b81b306be717091ac":{"statistic":{"failed":0,"broken":0,"skipped":0,"passed":1,"unknown":0,"total":1},"items":[{"uid":"6416a08bc048032","reportUrl":"https://DSahalatyi.github.io/test/24//#testresult/6416a08bc048032","status":"passed","time":{"start":1677436024373,"stop":1677436024380,"duration":7}}]},"f55e42df989f171c440453e5fd6da59e":{"statistic":{"failed":0,"broken":0,"skipped":0,"passed":1,"unknown":0,"total":1},"items":[{"uid":"a47ebec4d1bbb2b6","reportUrl":"https://DSahalatyi.github.io/test/24//#testresult/a47ebec4d1bbb2b6","status":"passed","time":{"start":1677436025644,"stop":1677436025688,"duration":44}}]},"721000aaca5efe5ed2d8eccc95216070":{"statistic":{"failed":0,"broken":0,"skipped":0,"passed":1,"unknown":0,"total":1},"items":[{"uid":"d6d054c545ccb388","reportUrl":"https://DSahalatyi.github.io/test/24//#testresult/d6d054c545ccb388","status":"passed","time":{"start":1677436025893,"stop":1677436025936,"duration":43}}]},"fb694134e9dabfe4563034e807bf3178":{"statistic":{"failed":0,"broken":0,"skipped":0,"passed":1,"unknown":0,"total":1},"items":[{"uid":"9f138953054dabea","reportUrl":"https://DSahalatyi.github.io/test/24//#testresult/9f138953054dabea","status":"passed","time":{"start":1677436018699,"stop":1677436018706,"duration":7}}]},"8426ea4855f02af446de7e6bc0f1a7bf":{"statistic":{"failed":0,"broken":0,"skipped":0,"passed":1,"unknown":0,"total":1},"items":[{"uid":"8c715d7d5d82fff2","reportUrl":"https://DSahalatyi.github.io/test/24//#testresult/8c715d7d5d82fff2","status":"passed","time":{"start":1677436012679,"stop":1677436012686,"duration":7}}]},"0914dc87c45580fe70b815622aec7266":{"statistic":{"failed":0,"broken":0,"skipped":0,"passed":1,"unknown":0,"total":1},"items":[{"uid":"33da3bd3b9450d00","reportUrl":"https://DSahalatyi.github.io/test/24//#testresult/33da3bd3b9450d00","status":"passed","time":{"start":1677436022828,"stop":1677436022832,"duration":4}}]},"df4e66e12b3ba211f9f64de1ad324abd":{"statistic":{"failed":0,"broken":0,"skipped":0,"passed":1,"unknown":0,"total":1},"items":[{"uid":"88b4e37ae82121f5","reportUrl":"https://DSahalatyi.github.io/test/24//#testresult/88b4e37ae82121f5","status":"passed","time":{"start":1677436022316,"stop":1677436022323,"duration":7}}]},"5ac54ad2f6a339a58b82df72130fa1e7":{"statistic":{"failed":0,"broken":0,"skipped":0,"passed":1,"unknown":0,"total":1},"items":[{"uid":"88a43a1ef18ed77d","reportUrl":"https://DSahalatyi.github.io/test/24//#testresult/88a43a1ef18ed77d","status":"passed","time":{"start":1677436017587,"stop":1677436017635,"duration":48}}]},"97d83b4f2b8426e4ea14f0f2175a7137":{"statistic":{"failed":0,"broken":0,"skipped":0,"passed":1,"unknown":0,"total":1},"items":[{"uid":"26ddaaab048471c5","reportUrl":"https://DSahalatyi.github.io/test/24//#testresult/26ddaaab048471c5","status":"passed","time":{"start":1677436014788,"stop":1677436014804,"duration":16}}]},"ff623025be8a44f4a360b4221dd85319":{"statistic":{"failed":0,"broken":0,"skipped":0,"passed":1,"unknown":0,"total":1},"items":[{"uid":"1f41fcc9f34e5e00","reportUrl":"https://DSahalatyi.github.io/test/24//#testresult/1f41fcc9f34e5e00","status":"passed","time":{"start":1677436028263,"stop":1677436028268,"duration":5}}]},"b819835e58110344f731f72581c1e06d":{"statistic":{"failed":0,"broken":0,"skipped":0,"passed":1,"unknown":0,"total":1},"items":[{"uid":"47a2c2d47559c4fb","reportUrl":"https://DSahalatyi.github.io/test/24//#testresult/47a2c2d47559c4fb","status":"passed","time":{"start":1677436010227,"stop":1677436010231,"duration":4}}]},"7ca383411bc7ae626fa2644ebe178b4c":{"statistic":{"failed":0,"broken":0,"skipped":0,"passed":1,"unknown":0,"total":1},"items":[{"uid":"8582bcefce5a9a6","reportUrl":"https://DSahalatyi.github.io/test/24//#testresult/8582bcefce5a9a6","status":"passed","time":{"start":1677436021220,"stop":1677436021269,"duration":49}}]},"34ef07efe63b8e66bc53baf9f4d1c934":{"statistic":{"failed":0,"broken":0,"skipped":0,"passed":1,"unknown":0,"total":1},"items":[{"uid":"a51b140abb34410e","reportUrl":"https://DSahalatyi.github.io/test/24//#testresult/a51b140abb34410e","status":"passed","time":{"start":1677436009601,"stop":1677436009608,"duration":7}}]},"e0388ae24586e3a3ba8614fd1be480ac":{"statistic":{"failed":0,"broken":0,"skipped":0,"passed":1,"unknown":0,"total":1},"items":[{"uid":"d1f07ef7afce17ac","reportUrl":"https://DSahalatyi.github.io/test/24//#testresult/d1f07ef7afce17ac","status":"passed","time":{"start":1677436020479,"stop":1677436020528,"duration":49}}]},"2be7d630c1a158e13a60f7d9f2667ac1":{"statistic":{"failed":0,"broken":0,"skipped":0,"passed":1,"unknown":0,"total":1},"items":[{"uid":"9f4ae0ff25a2650a","reportUrl":"https://DSahalatyi.github.io/test/24//#testresult/9f4ae0ff25a2650a","status":"passed","time":{"start":1677436011617,"stop":1677436011662,"duration":45}}]},"365eecdbe5c7916b12403094ca0df32a":{"statistic":{"failed":0,"broken":0,"skipped":0,"passed":1,"unknown":0,"total":1},"items":[{"uid":"57f48bf6f7ce1321","reportUrl":"https://DSahalatyi.github.io/test/24//#testresult/57f48bf6f7ce1321","status":"passed","time":{"start":1677436008326,"stop":1677436008388,"duration":62}}]},"ef07798248ebaaeed340dbfdb8169b3e":{"statistic":{"failed":0,"broken":0,"skipped":0,"passed":1,"unknown":0,"total":1},"items":[{"uid":"ea8f1299f4b2e7db","reportUrl":"https://DSahalatyi.github.io/test/24//#testresult/ea8f1299f4b2e7db","status":"passed","time":{"start":1677436017031,"stop":1677436017035,"duration":4}}]},"3a5d3e326c0e38786a8401b3e759bdde":{"statistic":{"failed":0,"broken":0,"skipped":0,"passed":1,"unknown":0,"total":1},"items":[{"uid":"c91a4ffb592e28ce","reportUrl":"https://DSahalatyi.github.io/test/24//#testresult/c91a4ffb592e28ce","status":"passed","time":{"start":1677436012359,"stop":1677436012363,"duration":4}}]},"c42dcdd9ec04cdc1d3215a2a6cb12702":{"statistic":{"failed":0,"broken":0,"skipped":0,"passed":1,"unknown":0,"total":1},"items":[{"uid":"a9a1ca0cd0bc40dc","reportUrl":"https://DSahalatyi.github.io/test/24//#testresult/a9a1ca0cd0bc40dc","status":"passed","time":{"start":1677436017201,"stop":1677436017207,"duration":6}}]},"539e7c7cbc261e2fdd1fb9066c47f47b":{"statistic":{"failed":0,"broken":0,"skipped":0,"passed":1,"unknown":0,"total":1},"items":[{"uid":"a5adf199d702433e","reportUrl":"https://DSahalatyi.github.io/test/24//#testresult/a5adf199d702433e","status":"passed","time":{"start":1677436014015,"stop":1677436014019,"duration":4}}]},"b597ff8468b9e646a8553b50cfcbc71f":{"statistic":{"failed":0,"broken":0,"skipped":0,"passed":1,"unknown":0,"total":1},"items":[{"uid":"410e28b44777db53","reportUrl":"https://DSahalatyi.github.io/test/24//#testresult/410e28b44777db53","status":"passed","time":{"start":1677436018922,"stop":1677436018927,"duration":5}}]},"9284e83119a93b65f7aa8ef087309eb5":{"statistic":{"failed":0,"broken":0,"skipped":0,"passed":1,"unknown":0,"total":1},"items":[{"uid":"2587a4af1cf012f1","reportUrl":"https://DSahalatyi.github.io/test/24//#testresult/2587a4af1cf012f1","status":"passed","time":{"start":1677436022105,"stop":1677436022151,"duration":46}}]},"29197cf98d69430dba36317eddc0e805":{"statistic":{"failed":0,"broken":0,"skipped":0,"passed":1,"unknown":0,"total":1},"items":[{"uid":"ad49c88e86c1ed8","reportUrl":"https://DSahalatyi.github.io/test/24//#testresult/ad49c88e86c1ed8","status":"passed","time":{"start":1677436020738,"stop":1677436020787,"duration":49}}]},"9df896d4f61befb30d1572fb4b2f017b":{"statistic":{"failed":0,"broken":0,"skipped":0,"passed":1,"unknown":0,"total":1},"items":[{"uid":"57f503733e95cb13","reportUrl":"https://DSahalatyi.github.io/test/24//#testresult/57f503733e95cb13","status":"passed","time":{"start":1677436019903,"stop":1677436019905,"duration":2}}]},"d72285be4eff4ca5b3bbbd87f4927d63":{"statistic":{"failed":0,"broken":0,"skipped":0,"passed":1,"unknown":0,"total":1},"items":[{"uid":"58f9d20c941e8a4","reportUrl":"https://DSahalatyi.github.io/test/24//#testresult/58f9d20c941e8a4","status":"passed","time":{"start":1677436023718,"stop":1677436023723,"duration":5}}]},"d5425985ed8c4b7f1207453a2acc6ebf":{"statistic":{"failed":0,"broken":0,"skipped":0,"passed":1,"unknown":0,"total":1},"items":[{"uid":"66343c0ff4c8178f","reportUrl":"https://DSahalatyi.github.io/test/24//#testresult/66343c0ff4c8178f","status":"passed","time":{"start":1677436008396,"stop":1677436008442,"duration":46}}]},"7c8f6c36009652d313b8fdb24b789e8d":{"statistic":{"failed":0,"broken":0,"skipped":0,"passed":1,"unknown":0,"total":1},"items":[{"uid":"af00b8e05b354538","reportUrl":"https://DSahalatyi.github.io/test/24//#testresult/af00b8e05b354538","status":"passed","time":{"start":1677436024606,"stop":1677436024616,"duration":10}}]},"dd565f5ed6318d87ed87bdeab0d8c8be":{"statistic":{"failed":0,"broken":0,"skipped":0,"passed":1,"unknown":0,"total":1},"items":[{"uid":"91b407eecc768142","reportUrl":"https://DSahalatyi.github.io/test/24//#testresult/91b407eecc768142","status":"passed","time":{"start":1677436010961,"stop":1677436011009,"duration":48}}]}}